understory/apps/webmention_endpoint/__init__.py
understory/apps/webmention_endpoint/templates/__init__.py
understory/apps/webmention_endpoint/templates/index.html
understory/apps/webmention_endpoint/templates/received/__init__.py
understory/apps/webmention_endpoint/templates/received/index.html
understory_webmention_endpoint-0.0.4.dist-info/entry_points.txt
understory_webmention_endpoint-0.0.4.dist-info/LICENSE
understory_webmention_endpoint-0.0.4.dist-info/WHEEL
understory_webmention_endpoint-0.0.4.dist-info/METADATA
understory_webmention_endpoint-0.0.4.dist-info/RECORD
